{"name":"soundcloud_livecoding","children":[{"name":"livecoding","children":[{"name":null,"value":66}]},{"name":"live coding","children":[{"name":null,"value":1}]},{"name":"","children":[{"name":null,"value":9}]},{"name":"supercollider","children":[{"name":null,"value":8}]},{"name":"Livecoding","children":[{"name":null,"value":11}]},{"name":"Drone","children":[{"name":null,"value":4}]},{"name":"LiveCoding","children":[{"name":null,"value":10}]},{"name":"LiveCoding SuperCollider","children":[{"name":null,"value":1}]},{"name":"Experimental Electronic","children":[{"name":null,"value":2}]},{"name":"Coding","children":[{"name":null,"value":1}]},{"name":"Live Coding","children":[{"name":null,"value":2}]},{"name":"demo","children":[{"name":null,"value":2}]},{"name":"SonicPi","children":[{"name":null,"value":1}]},{"name":"powers of 2","children":[{"name":null,"value":2}]},{"name":"Livecode","children":[{"name":null,"value":2}]},{"name":"algorave","children":[{"name":null,"value":20}]},{"name":"tabla","children":[{"name":null,"value":1}]},{"name":"Experimental","children":[{"name":null,"value":4}]},{"name":"DIY digital instruments","children":[{"name":null,"value":1}]},{"name":"caosbox","children":[{"name":null,"value":1}]},{"name":"lovecoding","children":[{"name":null,"value":1}]},{"name":"Folk","children":[{"name":null,"value":1}]},{"name":"performance","children":[{"name":null,"value":2}]},{"name":"neone","children":[{"name":null,"value":1}]},{"name":"networkmusic","children":[{"name":null,"value":1}]},{"name":"whistling","children":[{"name":null,"value":88}]},{"name":"live","children":[{"name":null,"value":11}]},{"name":"electronic","children":[{"name":null,"value":7}]},{"name":"Electronic","children":[{"name":null,"value":8}]},{"name":"Live Recordings","children":[{"name":null,"value":1}]},{"name":"Techno","children":[{"name":null,"value":1}]},{"name":"Algorave","children":[{"name":null,"value":3}]},{"name":"livecode","children":[{"name":null,"value":6}]},{"name":"ChucK","children":[{"name":null,"value":3}]},{"name":"liveCoding","children":[{"name":null,"value":1}]},{"name":"study","children":[{"name":null,"value":1}]},{"name":"compilation","children":[{"name":null,"value":2}]},{"name":"Tidal","children":[{"name":null,"value":2}]},{"name":"experimental","children":[{"name":null,"value":1}]},{"name":"offzz","children":[{"name":null,"value":1}]},{"name":"laptronica","children":[{"name":null,"value":2}]},{"name":"Laptronica","children":[{"name":null,"value":1}]},{"name":"Sonic Multiplicities","children":[{"name":null,"value":1}]},{"name":"noise","children":[{"name":null,"value":1}]},{"name":"electroacoustic","children":[{"name":null,"value":1}]},{"name":"Sound of Space","children":[{"name":null,"value":1}]},{"name":"improvisation","children":[{"name":null,"value":2}]},{"name":"Live","children":[{"name":null,"value":3}]},{"name":"LiveCode","children":[{"name":null,"value":1}]},{"name":"supercollider #live coding","children":[{"name":null,"value":1}]},{"name":"lumber","children":[{"name":null,"value":1}]},{"name":"dark interpreter","children":[{"name":null,"value":1}]},{"name":"bass music","children":[{"name":null,"value":1}]},{"name":"computermusic","children":[{"name":null,"value":1}]},{"name":"network music","children":[{"name":null,"value":1}]},{"name":"ambient gabba","children":[{"name":null,"value":1}]},{"name":"Piano Improvisation","children":[{"name":null,"value":1}]},{"name":"experimenetal","children":[{"name":null,"value":1}]},{"name":"hackpact","children":[{"name":null,"value":4}]},{"name":"tidal","children":[{"name":null,"value":2}]},{"name":null,"children":[{"name":null,"value":1}]},{"name":"pico_rave","children":[{"name":null,"value":1}]},{"name":"pelase","children":[{"name":null,"value":1}]},{"name":"Data","children":[{"name":null,"value":1}]},{"name":"Noise","children":[{"name":null,"value":2}]},{"name":"zx spectrum","children":[{"name":null,"value":1}]},{"name":"algorithmic composition","children":[{"name":null,"value":1}]},{"name":"Ambient","children":[{"name":null,"value":1}]},{"name":"algoetry","children":[{"name":null,"value":1}]},{"name":"Contemporary","children":[{"name":null,"value":1}]},{"name":"Future","children":[{"name":null,"value":1}]},{"name":"radio","children":[{"name":null,"value":1}]},{"name":"Live code","children":[{"name":null,"value":1}]},{"name":"drone","children":[{"name":null,"value":1}]},{"name":"WhiteNoise","children":[{"name":null,"value":1}]},{"name":"videocousmatic","children":[{"name":null,"value":1}]}]}